skysurvey_sniapop/__init__.py
skysurvey_sniapop/agepop.py
skysurvey_sniapop/hostmass.py
skysurvey_sniapop/lss.py
skysurvey_sniapop/magnitude.py
skysurvey_sniapop/models.py
skysurvey_sniapop/utils.py
skysurvey_sniapop-0.3.1.dist-info/LICENSE
skysurvey_sniapop-0.3.1.dist-info/METADATA
skysurvey_sniapop-0.3.1.dist-info/WHEEL
skysurvey_sniapop-0.3.1.dist-info/top_level.txt
skysurvey_sniapop-0.3.1.dist-info/RECORD
